datapizza/agents/__init__.py
datapizza/agents/__version__.py
datapizza/agents/agent.py
datapizza/agents/client_manager.py
datapizza/agents/logger.py
datapizza/agents/tests/test_base_agents.py
datapizza/cache/__init__.py
datapizza/clients/__init__.py
datapizza/clients/factory.py
datapizza/clients/mock_client.py
datapizza/core/__init__.py
datapizza/core/__version__.py
datapizza/core/constants.py
datapizza/core/models.py
datapizza/core/utils.py
datapizza/core/cache/__init__.py
datapizza/core/cache/cache.py
datapizza/core/clients/__init__.py
datapizza/core/clients/client.py
datapizza/core/clients/models.py
datapizza/core/clients/tests/test_mock_client.py
datapizza/core/clients/tests/test_token_usage.py
datapizza/core/embedder/__init__.py
datapizza/core/embedder/base.py
datapizza/core/executors/async_executor.py
datapizza/core/modules/captioner.py
datapizza/core/modules/metatagger.py
datapizza/core/modules/parser.py
datapizza/core/modules/prompt.py
datapizza/core/modules/reranker.py
datapizza/core/modules/rewriter.py
datapizza/core/modules/splitter.py
datapizza/core/vectorstore/__init__.py
datapizza/core/vectorstore/vectorstore.py
datapizza/core/vectorstore/tests/test_vectorstore_models.py
datapizza/embedders/__init__.py
datapizza/embedders/embedders.py
datapizza/memory/__init__.py
datapizza/memory/__version__.py
datapizza/memory/memory.py
datapizza/memory/memory_adapter.py
datapizza/memory/tests/__init__.py
datapizza/memory/tests/test_memory.py
datapizza/modules/captioners/__init__.py
datapizza/modules/captioners/llm_captioner.py
datapizza/modules/metatagger/__init__.py
datapizza/modules/metatagger/keyword_metatagger.py
datapizza/modules/metatagger/tests/test_keyword_metagger.py
datapizza/modules/parsers/__init__.py
datapizza/modules/parsers/md_parser.py
datapizza/modules/parsers/text_parser.py
datapizza/modules/parsers/tests/test_base_parser.py
datapizza/modules/parsers/tests/test_md_parser.py
datapizza/modules/prompt/__init__.py
datapizza/modules/prompt/image_rag.py
datapizza_ai_core-0.0.19.dist-info/METADATA
datapizza_ai_core-0.0.19.dist-info/WHEEL
datapizza_ai_core-0.0.19.dist-info/RECORD
