Metadata-Version: 2.4
Name: datapizza-ai-core
Version: 0.0.19
Summary: Core components for the datapizza-ai framework
License: MIT
Classifier: License :: OSI Approved :: MIT License
Classifier: Operating System :: OS Independent
Classifier: Programming Language :: Python :: 3
Requires-Python: <3.14,>=3.10.0
Requires-Dist: jinja2>=3.1.6
Requires-Dist: jsonref>=1.1.0
Requires-Dist: mcp>=1.20.0
Requires-Dist: opentelemetry-api>=1.33.1
Requires-Dist: opentelemetry-sdk>=1.33.1
Requires-Dist: pydantic<3.0.0,>=2.10.5
Requires-Dist: python-dotenv>=1.0.1
Requires-Dist: pyyaml>=6.0.2
Requires-Dist: rich>=14.1.0
Requires-Dist: typing-extensions<5.0.0,>=4.12.2
